bristoSOFTContacts-0.17.data/scripts/main.py
control/__init__.py
control/bristo_exceptions.py
control/bristocache.py
control/bristoprint.py
control/controller.py
control/internet.py
control/main.py
control/secure.py
control/speedtest.py
control/view.py
interface/__init__.py
interface/changepwd.py
interface/contacts.py
interface/contactsmain.py
interface/login.py
interface/newgroup.py
interface/resources_rc.py
interface/search.py
interface/searchgroup.py
testing/__init__.py
testing/test_controller.py
testing/test_internet.py
testing/test_secure.py
bristoSOFTContacts-0.17.dist-info/LICENSE
bristoSOFTContacts-0.17.dist-info/METADATA
bristoSOFTContacts-0.17.dist-info/WHEEL
bristoSOFTContacts-0.17.dist-info/top_level.txt
bristoSOFTContacts-0.17.dist-info/RECORD
