Metadata-Version: 2.1
Name: bristoSOFTContacts
Version: 0.17
Summary: bristoSOFT Contacts(tm) is a group oriented contacts managment system.
Home-page: https://bitbucket.org/bristolians/bristosoftcontacts/src/master/
Author: Kirk A Jackson
Author-email: jacksonirka@bristosoft.org
License: UNKNOWN
Keywords: contacts people sales cms friends groups
Platform: UNKNOWN
Classifier: Programming Language :: Python :: 3
Classifier: License :: OSI Approved :: MIT License
Classifier: Operating System :: OS Independent
Requires-Python: >=3.6
Requires-Dist: PyQt5
Requires-Dist: PyQt5-sip
Requires-Dist: psycopg2-binary
Requires-Dist: requests
